{"Loots":[
	{
		"slime": [
			{
				"id" : 0,
				"percent": 60
			},
			{
				"id" : 1,
				"percent" : 100
			}
		],
		"bat": [
			{
				"id" : 2,
				"percent": 50
			},
			{
				"id" : 3,
				"percent" : 90
			},
			{
				"id" : 4,
				"percent" : 100
			}
		],
		"spikySlime": [
			{
				"id" : 1,
				"percent": 40
			},
			{
				"id" : 5,
				"percent" : 100
			}
		],
		"zombie": [
			{
				"id" : 9,
				"percent": 60
			},
			{
				"id" : 6,
				"percent" : 95
			},
			{
				"id" : 7,
				"percent" : 100
			}
		],
		"carnivorPlant": [
			{
				"id" : 8,
				"percent": 55
			},
			{
				"id" : 9,
				"percent" : 100
			}
		],
		"skeleton": [
			{
				"id" : 10,
				"percent": 50
			},
			{
				"id" : 11,
				"percent" : 95
			},
			{
				"id" : 16,
				"percent" : 100
			}
		],
		"mummy": [
			{
				"id" : 10,
				"percent": 50
			},
			{
				"id" : 12,
				"percent" : 100
			}
		],
		"pyramidRock": [
			{
				"id" : 10,
				"percent": 60
			},
			{
				"id" : 13,
				"percent": 85
			},
			{
				"id" : 14,
				"percent" : 100
			}
		],
		"desertSoul": [
			{
				"id" : 11,
				"percent": 60
			},
			{
				"id" : 15,
				"percent" : 90
			},
			{
				"id" : 16,
				"percent" : 100
			}
		],
		"golem": [
			{
				"id" : 13,
				"percent": 65
			},
			{
				"id" : 14,
				"percent" : 85
			},
			{
				"id" : 17,
				"percent" : 100
			}
		],
		"iceMonster": [
			{
				"id" : 18,
				"percent" : 70
			},
			{
				"id" : 19,
				"percent" : 100
			}
		],
		"wolf": [
			{
				"id" : 2,
				"percent": 30
			},
			{
				"id" : 20,
				"percent" : 60
			},
			{
				"id" : 19,
				"percent" : 100
			}
		],
		"medusa": [
			{
				"id" : 6,
				"percent": 45
			},
			{
				"id" : 21,
				"percent" : 90
			},
			{
				"id" : 24,
				"percent" : 100
			}
		],
		"iceAnomaly": [
			{
				"id" : 22,
				"percent": 60
			},
			{
				"id" : 19,
				"percent" : 85
			},
			{
				"id" : 24,
				"percent" : 100
			}
		],
		"babyIceDragon": [
			{
				"id" : 18,
				"percent": 30
			},
			{
				"id" : 20,
				"percent" : 60
			},
			{
				"id" : 23,
				"percent" : 95
			},
			{
				"id" : 25,
				"percent" : 100
			}
		]

	}
]}